calmcarz/__init__.py
calmcarz/calm.py
calmcarz/carz.py
calmcarz-0.1.1.dist-info/licenses/LICENSE
calmcarz-0.1.1.dist-info/METADATA
calmcarz-0.1.1.dist-info/WHEEL
calmcarz-0.1.1.dist-info/top_level.txt
calmcarz-0.1.1.dist-info/RECORD
