Metadata-Version: 2.4
Name: calmcarz
Version: 0.1.1
Summary: A Python package for batch correction (CALM) and activity scoring (CARZ, TAS) of gene expression data.
Author-email: Yue Wang <yuw90@pitt.edu>
License: Copyright 2025 Yue Wang
Project-URL: Homepage, https://github.com/lenore-yue/calmcarz-package
Project-URL: Issues, https://github.com/lenore-yue/calmcarz-package/issues
Classifier: Programming Language :: Python :: 3
Classifier: License :: OSI Approved :: MIT License
Classifier: Operating System :: OS Independent
Classifier: Intended Audience :: Science/Research
Classifier: Topic :: Scientific/Engineering :: Bio-Informatics
Requires-Python: >=3.8
License-File: LICENSE
Requires-Dist: numpy
Requires-Dist: pandas
Requires-Dist: anndata
Requires-Dist: statsmodels
Requires-Dist: scipy
Requires-Dist: tqdm
Requires-Dist: typing
Dynamic: license-file
